<?xml version="1.0" encoding="utf-8" ?>
<dwsync>
<file name="austria.gif" server="ftp.joederose.us/public_html/" local="130931383849507366" remote="130933219200000000" />
<file name="Belize.gif" server="ftp.joederose.us/public_html/" local="130931383849927394" remote="130933219200000000" />
<file name="Egypt.gif" server="ftp.joederose.us/public_html/" local="130931383850027455" remote="130933219200000000" />
<file name="france.gif" server="ftp.joederose.us/public_html/" local="130931383850117468" remote="130933219200000000" />
<file name="germany.gif" server="ftp.joederose.us/public_html/" local="130931383850198334" remote="130933219200000000" />
<file name="Guatemala.gif" server="ftp.joederose.us/public_html/" local="130931383850298322" remote="130933219200000000" />
<file name="ireland.gif" server="ftp.joederose.us/public_html/" local="130931383850597697" remote="130933219200000000" />
<file name="Israel.gif" server="ftp.joederose.us/public_html/" local="130931383850677724" remote="130933219200000000" />
<file name="italy.gif" server="ftp.joederose.us/public_html/" local="130931383850778160" remote="130933219200000000" />
<file name="liechtenstein.gif" server="ftp.joederose.us/public_html/" local="130931383850908234" remote="130933219800000000" />
<file name="Mexico.gif" server="ftp.joederose.us/public_html/" local="130931383850978987" remote="130933219800000000" />
<file name="monaco.gif" server="ftp.joederose.us/public_html/" local="130931383851048444" remote="130933219800000000" />
<file name="Netherlands.gif" server="ftp.joederose.us/public_html/" local="130931383851114002" remote="130933219800000000" />
<file name="PalestinianAuthority.gif" server="ftp.joederose.us/public_html/" local="130931383851184509" remote="130933219800000000" />
<file name="sanmarino.gif" server="ftp.joederose.us/public_html/" local="130931383851253986" remote="130933219800000000" />
<file name="seborga.gif" server="ftp.joederose.us/public_html/" local="130931383851313993" remote="130933219800000000" />
<file name="switzerland.gif" server="ftp.joederose.us/public_html/" local="130931383851403992" remote="130933219800000000" />
<file name="uk.gif" server="ftp.joederose.us/public_html/" local="130931383851504012" remote="130933219800000000" />
<file name="usa.gif" server="ftp.joederose.us/public_html/" local="130931383851574006" remote="130933219800000000" />
</dwsync>